dfu/__init__.py
dfu/dfu_cc_pb2.py
nrf_pk/__init__.py
nrf_pk/__main__.py
nrf_pk/find_pk.py
nrf_pk-0.0.6.dist-info/LICENSE
nrf_pk-0.0.6.dist-info/METADATA
nrf_pk-0.0.6.dist-info/WHEEL
nrf_pk-0.0.6.dist-info/entry_points.txt
nrf_pk-0.0.6.dist-info/top_level.txt
nrf_pk-0.0.6.dist-info/RECORD
