Metadata-Version: 2.1
Name: nrf-pk
Version: 0.0.6
Summary: Finds ECDSA public key in Nordic bootloader image
Author-email: Dmitriy Dyomin <dmitrodem@gmail.com>
Project-URL: Homepage, https://github.com/dmitrodem/nrf_pk
Project-URL: Bug Tracker, https://github.com/dmitrodem/nrf_pk/issues
Classifier: Programming Language :: Python :: 3
Classifier: License :: OSI Approved :: MIT License
Classifier: Operating System :: OS Independent
Requires-Python: >=3.7
License-File: LICENSE
Requires-Dist: protobuf
Requires-Dist: click
Requires-Dist: ecdsa
